{
  "empleados": [
    "Juan Perez",
    "Maria Garcia"
  ],
  "calendariosPorMes": [ // Nuevo array para el historial
    {
      "mesAnio": "2025-07", // Formato YYYY-MM
      "fechasGeneradas": "2025-07-01", // Fecha en que se generó este mes (para referencia)
      "calendarioMensual": [ // El calendario de ese mes específico
        {
          "name": "Juan Perez",
          "schedule": [
            { "date": "2025-07-01", "status": "Oficina" },
            { "date": "2025-07-02", "status": "Remoto" }
          ]
        },
        {
          "name": "Maria Garcia",
          "schedule": [
            { "date": "2025-07-01", "status": "Remoto" }
          ]
        }
      ]
    },
    {
      "mesAnio": "2025-08",
      "fechasGeneradas": "2025-07-24",
      "calendarioMensual": [
         // ... datos del calendario de agosto ...
      ]
    }
  ],
  "currentCalendarData": { // Este mantendrá solo el calendario que se está visualizando/editando actualmente
    "empleadosEnCalendario": [ "Juan Perez", "Maria Garcia" ], // Lista de empleados activos en la vista actual
    "scheduleData": [
        // ... el contenido actual de 'calendar' se movería aquí para la edición activa ...
    ]
  }
}
