{
  "registros": [
    {
      "id": 1751309857088,
      "fecha": "2025-06-23",
      "tipoMovimiento": "Ingreso",
      "cantidad": 10,
      "ancho": 100,
      "alto": 100,
      "material": "Concreto",
      "sigest": "1",
      "origen": "retesar"
    },
    {
      "id": 1751310026480,
      "fecha": "2025-06-30",
      "tipoMovimiento": "Consumo",
      "cantidad": 5,
      "ancho": 100,
      "alto": 100,
      "material": "Concreto",
      "sigest": "65",
      "origen": "mop"
    },
    {
      "id": 1751310447199,
      "fecha": "2025-06-30",
      "tipoMovimiento": "Ingreso",
      "cantidad": 200,
      "ancho": 40,
      "alto": 40,
      "material": "Concreto",
      "sigest": "",
      "origen": "retesar"
    },
    {
      "id": 1751310472814,
      "fecha": "2025-06-24",
      "tipoMovimiento": "Ingreso",
      "cantidad": 6,
      "ancho": 100,
      "alto": 100,
      "material": "Concreto",
      "sigest": "",
      "origen": "mop"
    }
  ]
}
